Metadata-Version: 2.1
Name: wadePyPITest
Version: 1.0
Summary: PyPI Tutorial
Home-page: https://github.com/
Author: wade
Author-email: beyondsjxc@163.com
License: UNKNOWN
Platform: UNKNOWN
Classifier: Programming Language :: Python :: 3
Classifier: License :: OSI Approved :: MIT License
Classifier: Operating System :: OS Independent
Requires-Python: >=3
